evalkit/__init__.py
evalkit/basic.py
evalkit/geal/__init__.py
evalkit/geal/algs.py
evalkit/geal/cross.py
evalkit/geal/inits.py
evalkit/geal/muts.py
evalkit/geal/sels.py
evalkit/sial/__init__.py
evalkit/sial/inits.py
evalkit/sial/muts.py
evalkit/tools/__init__.py
evalkit/tools/statslog.py
evalkit-0.2.1.dist-info/LICENSE
evalkit-0.2.1.dist-info/METADATA
evalkit-0.2.1.dist-info/WHEEL
evalkit-0.2.1.dist-info/top_level.txt
evalkit-0.2.1.dist-info/RECORD
