Metadata-Version: 2.1
Name: evalkit
Version: 0.2.1
Summary: EVolutionary ALgorithms KITs
Home-page: https://github.com/parvector/evalkit
Author: Parviz Mirzoev
Author-email: parvector@yandex.com
License: UNKNOWN
Platform: UNKNOWN
Requires-Dist: numpy
